ali_base_service
